diffusers/__init__.py
diffusers/configuration_utils.py
diffusers/dependency_versions_check.py
diffusers/dependency_versions_table.py
diffusers/image_processor.py
diffusers/optimization.py
diffusers/py.typed
diffusers/training_utils.py
diffusers/commands/__init__.py
diffusers/commands/diffusers_cli.py
diffusers/commands/env.py
diffusers/commands/fp16_safetensors.py
diffusers/experimental/__init__.py
diffusers/experimental/rl/__init__.py
diffusers/experimental/rl/value_guided_sampling.py
diffusers/loaders/__init__.py
diffusers/loaders/ip_adapter.py
diffusers/loaders/lora.py
diffusers/loaders/lora_conversion_utils.py
diffusers/loaders/single_file.py
diffusers/loaders/textual_inversion.py
diffusers/loaders/unet.py
diffusers/loaders/utils.py
diffusers/models/__init__.py
diffusers/models/activations.py
diffusers/models/adapter.py
diffusers/models/attention.py
diffusers/models/attention_flax.py
diffusers/models/attention_processor.py
diffusers/models/autoencoder_asym_kl.py
diffusers/models/autoencoder_kl.py
diffusers/models/autoencoder_kl_temporal_decoder.py
diffusers/models/autoencoder_tiny.py
diffusers/models/consistency_decoder_vae.py
diffusers/models/controlnet.py
diffusers/models/controlnet_flax.py
diffusers/models/controlnetxs.py
diffusers/models/dual_transformer_2d.py
diffusers/models/embeddings.py
diffusers/models/embeddings_flax.py
diffusers/models/lora.py
diffusers/models/modeling_flax_pytorch_utils.py
diffusers/models/modeling_flax_utils.py
diffusers/models/modeling_outputs.py
diffusers/models/modeling_pytorch_flax_utils.py
diffusers/models/modeling_utils.py
diffusers/models/normalization.py
diffusers/models/prior_transformer.py
diffusers/models/resnet.py
diffusers/models/resnet_flax.py
diffusers/models/t5_film_transformer.py
diffusers/models/transformer_2d.py
diffusers/models/transformer_temporal.py
diffusers/models/unet_1d.py
diffusers/models/unet_1d_blocks.py
diffusers/models/unet_2d.py
diffusers/models/unet_2d_blocks.py
diffusersv-0.25.dev0.dist-info/LICENSE
diffusersv-0.25.dev0.dist-info/METADATA
diffusersv-0.25.dev0.dist-info/WHEEL
diffusersv-0.25.dev0.dist-info/entry_points.txt
diffusersv-0.25.dev0.dist-info/top_level.txt
diffusersv-0.25.dev0.dist-info/RECORD
